tudata/__init__.py
tudata/core.py
tudata-1.0.7.dist-info/licenses/LICENSE
tudata-1.0.7.dist-info/METADATA
tudata-1.0.7.dist-info/WHEEL
tudata-1.0.7.dist-info/top_level.txt
tudata-1.0.7.dist-info/RECORD
