Metadata-Version: 2.4
Name: tudata
Version: 1.0.7
Summary: A Python library for accessing Tushare financial data through optimized API
Author-email: fuconx <contact@tudata.com>
Maintainer-email: fuconx <contact@tudata.com>
Project-URL: Homepage, https://github.com/fuconx/tudata
Project-URL: Documentation, https://tudata.readthedocs.io
Project-URL: Repository, https://github.com/fuconx/tudata.git
Project-URL: Bug Tracker, https://github.com/fuconx/tudata/issues
Keywords: finance,data,tushare,stock,market
Classifier: Development Status :: 4 - Beta
Classifier: Intended Audience :: Developers
Classifier: Intended Audience :: Financial and Insurance Industry
Classifier: Programming Language :: Python :: 3
Classifier: Programming Language :: Python :: 3.7
Classifier: Programming Language :: Python :: 3.8
Classifier: Programming Language :: Python :: 3.9
Classifier: Programming Language :: Python :: 3.10
Classifier: Programming Language :: Python :: 3.11
Classifier: Topic :: Office/Business :: Financial
Classifier: Topic :: Software Development :: Libraries :: Python Modules
Requires-Python: >=3.7
License-File: LICENSE
Requires-Dist: requests>=2.25.0
Requires-Dist: pandas>=1.0.0
Requires-Dist: urllib3>=1.26.0
Provides-Extra: dev
Requires-Dist: pytest>=6.0; extra == "dev"
Requires-Dist: pytest-cov>=2.0; extra == "dev"
Requires-Dist: black>=21.0; extra == "dev"
Requires-Dist: flake8>=3.8; extra == "dev"
Requires-Dist: mypy>=0.800; extra == "dev"
Dynamic: license-file
